rheedium/__init__.py
rheedium/_luggage/Kirkland_Potentials.csv
rheedium/_luggage/atom_colors.json
rheedium/_luggage/atom_numbers.json
rheedium/inout/__init__.py
rheedium/inout/cif.py
rheedium/inout/crystal.py
rheedium/inout/interop.py
rheedium/inout/poscar.py
rheedium/inout/py.typed
rheedium/inout/vaspxml.py
rheedium/inout/xyz.py
rheedium/plots/__init__.py
rheedium/plots/diagrams.py
rheedium/plots/figuring.py
rheedium/plots/py.typed
rheedium/py.typed
rheedium/recon/__init__.py
rheedium/recon/py.typed
rheedium/simul/__init__.py
rheedium/simul/ewald.py
rheedium/simul/finite_domain.py
rheedium/simul/form_factors.py
rheedium/simul/kinematic.py
rheedium/simul/py.typed
rheedium/simul/simul_utils.py
rheedium/simul/simulator.py
rheedium/simul/surface_rods.py
rheedium/types/__init__.py
rheedium/types/crystal_types.py
rheedium/types/custom_types.py
rheedium/types/py.typed
rheedium/types/rheed_types.py
rheedium/ucell/__init__.py
rheedium/ucell/bessel.py
rheedium/ucell/helper.py
rheedium/ucell/py.typed
rheedium/ucell/unitcell.py
rheedium-2025.10.10.dist-info/WHEEL
rheedium-2025.10.10.dist-info/METADATA
rheedium-2025.10.10.dist-info/RECORD
